README.md
setup.py
spider_commonah.egg-info/PKG-INFO
spider_commonah.egg-info/SOURCES.txt
spider_commonah.egg-info/dependency_links.txt
spider_commonah.egg-info/requires.txt
spider_commonah.egg-info/top_level.txt
src/__init__.py
src/config.py
src/m3u8_utils.py
src/request_session.py
src/sink_tools.py
src/track_tools.py
src/verify_code.py
src/xpath_json.py
utils/__init__.py
utils/enum_classify.py
utils/file_utils.py
utils/request_utils.py
utils/string_utils.py