Metadata-Version: 2.1
Name: spider-commonah
Version: 0.0.3
Summary: spdier 工具模块,修复 0.0.2 版本的 一些bug
Home-page: https://github.com/
Author: MR.AH
Author-email: zhangzhonghui1001@gmail.com
Classifier: Programming Language :: Python :: 3
Classifier: License :: OSI Approved :: MIT License
Classifier: Operating System :: OS Independent
Requires-Python: >=3.9
Requires-Dist: openpyxl==3.1.2
Requires-Dist: tqdm==4.66.2
